<?xml version="1.0" encoding="UTF-8" ?>
<!DOCTYPE struts PUBLIC
        "-//Apache Software Foundation//DTD Struts Configuration 2.1//EN"
        "http://struts.apache.org/dtds/struts-2.1.dtd">
<struts>
    <package name="log" extends="cement-interceptor">
        <action name="querylogs" method="queryLogs"
                class="com.channel.log.LogAction">
            <result name="json" type="json">
                <param name="root">result</param>
                <param name="ignoreHierarchy">false</param>
            </result>
        </action>

        <action name="dellogs" method="delLogs"
                class="com.channel.log.LogAction">
            <result name="json" type="json">
                <param name="root">result</param>
                <param name="ignoreHierarchy">false</param>
            </result>
        </action>
    </package>
</struts>

